Metadata-Version: 2.1
Name: trashtra
Version: 0.0.1
Summary: some ***
Home-page: UNKNOWN
Author: leene
Author-email: ivaschenkoanastas@gmail.com
License: UNKNOWN
Platform: UNKNOWN
